http_backuper/__init__.py
http_backuper/backuper.py
http_backuper/models.py
tests/__init__.py
tests/tests.py
http_backuper-0.1.5.dist-info/LICENSE
http_backuper-0.1.5.dist-info/METADATA
http_backuper-0.1.5.dist-info/WHEEL
http_backuper-0.1.5.dist-info/entry_points.txt
http_backuper-0.1.5.dist-info/top_level.txt
http_backuper-0.1.5.dist-info/RECORD
